Metadata-Version: 2.1
Name: hypixelapi
Version: 0.1.4
Summary: A Python 3 wrapper for the HypixelAPI
Home-page: https://github.com/MylesMor/hypixelapi
Author: MylesMor
Author-email: hello@mylesmor.dev
License: MIT
Platform: UNKNOWN
Classifier: Programming Language :: Python :: 3
Classifier: License :: OSI Approved :: MIT License
Classifier: Operating System :: OS Independent
Requires-Python: >=3.6
